makerpy/__init__.py
makerpy/test.py
makerpy-0.0.2.0.dist-info/LICENCE.txt
makerpy-0.0.2.0.dist-info/METADATA
makerpy-0.0.2.0.dist-info/WHEEL
makerpy-0.0.2.0.dist-info/top_level.txt
makerpy-0.0.2.0.dist-info/RECORD
